[
    {
        "nome": "Ghiggia ingegneria d'impianti s.r.l.",
        "href": "/Azienda_GHIGGIA-INGEGNERIA-DIMPIANTI-SRL",
        "href_details": "https://www.informazione-aziende.it/Azienda_GHIGGIA-INGEGNERIA-DIMPIANTI-SRL"
    },
    {
        "nome": "Agrolabo - s.p.a.",
        "href": "/Azienda_AGROLABO-SPA",
        "href_details": "https://www.informazione-aziende.it/Azienda_AGROLABO-SPA"
    },
    {
        "nome": "Gli argonauti societa' cooperativa sociale onlus siglabile gli argonauti s.c.s. onlus",
        "href": "/Azienda_GLI-ARGONAUTI-SOCIETA-COOPERATIVA-SOCIALE-ONLUS-SIGLABILE-GLI-ARGONAUTI-SCS-ONLUS",
        "href_details": "https://www.informazione-aziende.it/Azienda_GLI-ARGONAUTI-SOCIETA-COOPERATIVA-SOCIALE-ONLUS-SIGLABILE-GLI-ARGONAUTI-SCS-ONLUS"
    },
    {
        "nome": "Lamp s.r.l.",
        "href": "/Azienda_LAMP-SRL-AC52F",
        "href_details": "https://www.informazione-aziende.it/Azienda_LAMP-SRL-AC52F"
    },
    {
        "nome": "I.m.g. international s.r.l.",
        "href": "/Azienda_IMG-INTERNATIONAL-SRL",
        "href_details": "https://www.informazione-aziende.it/Azienda_IMG-INTERNATIONAL-SRL"
    },
    {
        "nome": "Atena nuove dimensioni s.r.l.",
        "href": "/Azienda_ATENA-NUOVE-DIMENSIONI-SRL",
        "href_details": "https://www.informazione-aziende.it/Azienda_ATENA-NUOVE-DIMENSIONI-SRL"
    },
    {
        "nome": "Alpem srl",
        "href": "/Azienda_ALPEM-SRL-473D3",
        "href_details": "https://www.informazione-aziende.it/Azienda_ALPEM-SRL-473D3"
    },
    {
        "nome": "Hospital service s.r.l.",
        "href": "/Azienda_HOSPITAL-SERVICE-SRL-CC50F",
        "href_details": "https://www.informazione-aziende.it/Azienda_HOSPITAL-SERVICE-SRL-CC50F"
    },
    {
        "nome": "C.s. motors s.r.l.",
        "href": "/Azienda_CS-MOTORS-SRL-76E67",
        "href_details": "https://www.informazione-aziende.it/Azienda_CS-MOTORS-SRL-76E67"
    },
    {
        "nome": "Quattro s.r.l.",
        "href": "/Azienda_QUATTRO-SRL-AA3CB",
        "href_details": "https://www.informazione-aziende.it/Azienda_QUATTRO-SRL-AA3CB"
    },
    {
        "nome": "Bvl serramenti srl",
        "href": "/Azienda_BVL-SERRAMENTI-SRL",
        "href_details": "https://www.informazione-aziende.it/Azienda_BVL-SERRAMENTI-SRL"
    },
    {
        "nome": "Model project - m.p. s.r.l.",
        "href": "/Azienda_MODEL-PROJECT-MP-SRL",
        "href_details": "https://www.informazione-aziende.it/Azienda_MODEL-PROJECT-MP-SRL"
    },
    {
        "nome": "Priuli & verlucca editori - s.r.l.",
        "href": "/Azienda_PRIULI-VERLUCCA-EDITORI-SRL",
        "href_details": "https://www.informazione-aziende.it/Azienda_PRIULI-VERLUCCA-EDITORI-SRL"
    },
    {
        "nome": "Sintesi s.r.l.",
        "href": "/Azienda_SINTESI-SRL-C61D9",
        "href_details": "https://www.informazione-aziende.it/Azienda_SINTESI-SRL-C61D9"
    },
    {
        "nome": "Zacchia srl",
        "href": "/Azienda_ZACCHIA-SRL",
        "href_details": "https://www.informazione-aziende.it/Azienda_ZACCHIA-SRL"
    },
    {
        "nome": "Teorema s.r.l.",
        "href": "/Azienda_TEOREMA-SRL-61D6F",
        "href_details": "https://www.informazione-aziende.it/Azienda_TEOREMA-SRL-61D6F"
    },
    {
        "nome": "Se.va. s.r.l.",
        "href": "/Azienda_SEVA-SRL-A33FA",
        "href_details": "https://www.informazione-aziende.it/Azienda_SEVA-SRL-A33FA"
    },
    {
        "nome": "Spes s.r.l.",
        "href": "/Azienda_SPES-SRL-0AC3D",
        "href_details": "https://www.informazione-aziende.it/Azienda_SPES-SRL-0AC3D"
    },
    {
        "nome": "Geodinamic s.r.l.",
        "href": "/Azienda_GEODINAMIC-SRL",
        "href_details": "https://www.informazione-aziende.it/Azienda_GEODINAMIC-SRL"
    },
    {
        "nome": "Officinamanzato srl",
        "href": "/Azienda_OFFICINAMANZATO-SRL",
        "href_details": "https://www.informazione-aziende.it/Azienda_OFFICINAMANZATO-SRL"
    },
    {
        "nome": "Locomad s.r.l.",
        "href": "/Azienda_LOCOMAD-SRL",
        "href_details": "https://www.informazione-aziende.it/Azienda_LOCOMAD-SRL"
    },
    {
        "nome": "Paform alimentare societa' a responsabilita' limitata semplificata",
        "href": "/Azienda_PAFORM-ALIMENTARE-SOCIETA-A-RESPONSABILITA-LIMITATA-SEMPLIFICATA",
        "href_details": "https://www.informazione-aziende.it/Azienda_PAFORM-ALIMENTARE-SOCIETA-A-RESPONSABILITA-LIMITATA-SEMPLIFICATA"
    },
    {
        "nome": "Olimpia s.r.l.",
        "href": "/Azienda_OLIMPIA-SRL-FFCF0",
        "href_details": "https://www.informazione-aziende.it/Azienda_OLIMPIA-SRL-FFCF0"
    },
    {
        "nome": "Inva  s.r.l.",
        "href": "/Azienda_INVA-SRL",
        "href_details": "https://www.informazione-aziende.it/Azienda_INVA-SRL"
    },
    {
        "nome": "Imla s.r.l.",
        "href": "/Azienda_IMLA-SRL",
        "href_details": "https://www.informazione-aziende.it/Azienda_IMLA-SRL"
    },
    {
        "nome": "Societa' consortile per la realizzazione e la gestione di imprese turistiche ed alberghiere s.c. a r.l. siglabile c.r.g. s.c. a r.l.",
        "href": "/Azienda_SOCIETA-CONSORTILE-PER-LA-REALIZZAZIONE-E-LA-GESTIONE-DI-IMPRESE-TURISTICHE-ED-ALBERGHIERE-SC-A-RL-SIGLABILE-CRG-SC-A-RL",
        "href_details": "https://www.informazione-aziende.it/Azienda_SOCIETA-CONSORTILE-PER-LA-REALIZZAZIONE-E-LA-GESTIONE-DI-IMPRESE-TURISTICHE-ED-ALBERGHIERE-SC-A-RL-SIGLABILE-CRG-SC-A-RL"
    },
    {
        "nome": "Fitness service srl",
        "href": "/Azienda_FITNESS-SERVICE-SRL-B1C03",
        "href_details": "https://www.informazione-aziende.it/Azienda_FITNESS-SERVICE-SRL-B1C03"
    },
    {
        "nome": "Ghiardi enrica",
        "href": "/Azienda_GHIARDI-ENRICA",
        "href_details": "https://www.informazione-aziende.it/Azienda_GHIARDI-ENRICA"
    },
    {
        "nome": "Mancin ermanno",
        "href": "/Azienda_MANCIN-ERMANNO",
        "href_details": "https://www.informazione-aziende.it/Azienda_MANCIN-ERMANNO"
    },
    {
        "nome": "Bessolo oscar",
        "href": "/Azienda_BESSOLO-OSCAR",
        "href_details": "https://www.informazione-aziende.it/Azienda_BESSOLO-OSCAR"
    },
    {
        "nome": "Minchillo francesco",
        "href": "/Azienda_MINCHILLO-FRANCESCO",
        "href_details": "https://www.informazione-aziende.it/Azienda_MINCHILLO-FRANCESCO"
    },
    {
        "nome": "Russi damaride",
        "href": "/Azienda_RUSSI-DAMARIDE",
        "href_details": "https://www.informazione-aziende.it/Azienda_RUSSI-DAMARIDE"
    },
    {
        "nome": "Manarin luca",
        "href": "/Azienda_MANARIN-LUCA",
        "href_details": "https://www.informazione-aziende.it/Azienda_MANARIN-LUCA"
    },
    {
        "nome": "Mauro lombardi",
        "href": "/Azienda_MAURO-LOMBARDI",
        "href_details": "https://www.informazione-aziende.it/Azienda_MAURO-LOMBARDI"
    },
    {
        "nome": "Xodo davide franco",
        "href": "/Azienda_XODO-DAVIDE-FRANCO",
        "href_details": "https://www.informazione-aziende.it/Azienda_XODO-DAVIDE-FRANCO"
    },
    {
        "nome": "Il cardallegro di loredana perla",
        "href": "/Azienda_IL-CARDALLEGRO-DI-LOREDANA-PERLA",
        "href_details": "https://www.informazione-aziende.it/Azienda_IL-CARDALLEGRO-DI-LOREDANA-PERLA"
    },
    {
        "nome": "Grosso franco",
        "href": "/Azienda_GROSSO-FRANCO-CC3DE",
        "href_details": "https://www.informazione-aziende.it/Azienda_GROSSO-FRANCO-CC3DE"
    },
    {
        "nome": "Carello ivan",
        "href": "/Azienda_CARELLO-IVAN",
        "href_details": "https://www.informazione-aziende.it/Azienda_CARELLO-IVAN"
    },
    {
        "nome": "Bessolo francesco",
        "href": "/Azienda_BESSOLO-FRANCESCO",
        "href_details": "https://www.informazione-aziende.it/Azienda_BESSOLO-FRANCESCO"
    },
    {
        "nome": "Azienda agricola massetto lilliana di grisoglio pier carlo",
        "href": "/Azienda_AZIENDA-AGRICOLA-MASSETTO-LILLIANA-DI-GRISOGLIO-PIER-CARLO",
        "href_details": "https://www.informazione-aziende.it/Azienda_AZIENDA-AGRICOLA-MASSETTO-LILLIANA-DI-GRISOGLIO-PIER-CARLO"
    },
    {
        "nome": "Grassani fabio",
        "href": "/Azienda_GRASSANI-FABIO",
        "href_details": "https://www.informazione-aziende.it/Azienda_GRASSANI-FABIO"
    },
    {
        "nome": "L'arciere di anglisani alexander",
        "href": "/Azienda_LARCIERE-DI-ANGLISANI-ALEXANDER",
        "href_details": "https://www.informazione-aziende.it/Azienda_LARCIERE-DI-ANGLISANI-ALEXANDER"
    },
    {
        "nome": "Bessolo venaria elio",
        "href": "/Azienda_BESSOLO-VENARIA-ELIO",
        "href_details": "https://www.informazione-aziende.it/Azienda_BESSOLO-VENARIA-ELIO"
    },
    {
        "nome": "Ronchi luigi",
        "href": "/Azienda_RONCHI-LUIGI",
        "href_details": "https://www.informazione-aziende.it/Azienda_RONCHI-LUIGI"
    },
    {
        "nome": "Vintage restaurant di danielova jana",
        "href": "/Azienda_VINTAGE-RESTAURANT-DI-DANIELOVA-JANA",
        "href_details": "https://www.informazione-aziende.it/Azienda_VINTAGE-RESTAURANT-DI-DANIELOVA-JANA"
    },
    {
        "nome": "Pioppo maria",
        "href": "/Azienda_PIOPPO-MARIA",
        "href_details": "https://www.informazione-aziende.it/Azienda_PIOPPO-MARIA"
    },
    {
        "nome": "Il piccolo emporio di sonia savastano",
        "href": "/Azienda_IL-PICCOLO-EMPORIO-DI-SONIA-SAVASTANO",
        "href_details": "https://www.informazione-aziende.it/Azienda_IL-PICCOLO-EMPORIO-DI-SONIA-SAVASTANO"
    },
    {
        "nome": "Prt pneumatici di peretto alessandro pietro",
        "href": "/Azienda_PRT-PNEUMATICI-DI-PERETTO-ALESSANDRO-PIETRO",
        "href_details": "https://www.informazione-aziende.it/Azienda_PRT-PNEUMATICI-DI-PERETTO-ALESSANDRO-PIETRO"
    },
    {
        "nome": "Maga maurizio enrico",
        "href": "/Azienda_MAGA-MAURIZIO-ENRICO",
        "href_details": "https://www.informazione-aziende.it/Azienda_MAGA-MAURIZIO-ENRICO"
    },
    {
        "nome": "Mosso ivo",
        "href": "/Azienda_MOSSO-IVO",
        "href_details": "https://www.informazione-aziende.it/Azienda_MOSSO-IVO"
    },
    {
        "nome": "Brunetti nicolo'",
        "href": "/Azienda_BRUNETTI-NICOLO",
        "href_details": "https://www.informazione-aziende.it/Azienda_BRUNETTI-NICOLO"
    },
    {
        "nome": "Zacchia giuseppe sas",
        "href": "/Azienda_ZACCHIA-GIUSEPPE-SAS",
        "href_details": "https://www.informazione-aziende.it/Azienda_ZACCHIA-GIUSEPPE-SAS"
    },
    {
        "nome": "3b s.n.c. di bessolo fabrizio e luca & c.",
        "href": "/Azienda_3B-SNC-DI-BESSOLO-FABRIZIO-E-LUCA-C",
        "href_details": "https://www.informazione-aziende.it/Azienda_3B-SNC-DI-BESSOLO-FABRIZIO-E-LUCA-C"
    },
    {
        "nome": "Impresa agricola massetto lilliana",
        "href": "/Azienda_IMPRESA-AGRICOLA-MASSETTO-LILLIANA",
        "href_details": "https://www.informazione-aziende.it/Azienda_IMPRESA-AGRICOLA-MASSETTO-LILLIANA"
    },
    {
        "nome": "Inzillo pasquale",
        "href": "/Azienda_INZILLO-PASQUALE",
        "href_details": "https://www.informazione-aziende.it/Azienda_INZILLO-PASQUALE"
    },
    {
        "nome": "Sps s.r.l.",
        "href": "/Azienda_SPS-SRL-27BDC",
        "href_details": "https://www.informazione-aziende.it/Azienda_SPS-SRL-27BDC"
    },
    {
        "nome": "Hotel ristorante stella bianca di bessolo alex e c. s.n.c.",
        "href": "/Azienda_HOTEL-RISTORANTE-STELLA-BIANCA-DI-BESSOLO-ALEX-E-C-SNC",
        "href_details": "https://www.informazione-aziende.it/Azienda_HOTEL-RISTORANTE-STELLA-BIANCA-DI-BESSOLO-ALEX-E-C-SNC"
    },
    {
        "nome": "Edilzeta di zacchia e plazio s.n.c.",
        "href": "/Azienda_EDILZETA-DI-ZACCHIA-E-PLAZIO-SNC",
        "href_details": "https://www.informazione-aziende.it/Azienda_EDILZETA-DI-ZACCHIA-E-PLAZIO-SNC"
    },
    {
        "nome": "Canaveselab3.0 di scagnolari sonia",
        "href": "/Azienda_CANAVESELAB30-DI-SCAGNOLARI-SONIA",
        "href_details": "https://www.informazione-aziende.it/Azienda_CANAVESELAB30-DI-SCAGNOLARI-SONIA"
    },
    {
        "nome": "Il sole di tesolin roberta lucia & c. sas",
        "href": "/Azienda_IL-SOLE-DI-TESOLIN-ROBERTA-LUCIA-C-SAS",
        "href_details": "https://www.informazione-aziende.it/Azienda_IL-SOLE-DI-TESOLIN-ROBERTA-LUCIA-C-SAS"
    },
    {
        "nome": "Circolo quattro chiacchiere assoc. ricreat. cultur. e polisport.",
        "href": "/Azienda_CIRCOLO-QUATTRO-CHIACCHIERE-ASSOC-RICREAT-CULTUR-E-POLISPORT",
        "href_details": "https://www.informazione-aziende.it/Azienda_CIRCOLO-QUATTRO-CHIACCHIERE-ASSOC-RICREAT-CULTUR-E-POLISPORT"
    },
    {
        "nome": "Ocra*officine costruzioni ricambi per autotrazione - societa' a responsabilita' limitata",
        "href": "/Azienda_OCRAOFFICINE-COSTRUZIONI-RICAMBI-PER-AUTOTRAZIONE-SOCIETA-A-RESPONSABILITA-LIMITATA",
        "href_details": "https://www.informazione-aziende.it/Azienda_OCRAOFFICINE-COSTRUZIONI-RICAMBI-PER-AUTOTRAZIONE-SOCIETA-A-RESPONSABILITA-LIMITATA"
    },
    {
        "nome": "Prima s.n.c. di carletti roberto & c.",
        "href": "/Azienda_PRIMA-SNC-DI-CARLETTI-ROBERTO-C",
        "href_details": "https://www.informazione-aziende.it/Azienda_PRIMA-SNC-DI-CARLETTI-ROBERTO-C"
    },
    {
        "nome": "Tecnoelettra s.n.c. di vercellono matteo oscar & c.",
        "href": "/Azienda_TECNOELETTRA-SNC-DI-VERCELLONO-MATTEO-OSCAR-C",
        "href_details": "https://www.informazione-aziende.it/Azienda_TECNOELETTRA-SNC-DI-VERCELLONO-MATTEO-OSCAR-C"
    },
    {
        "nome": "A.v.e.a di bessolo elvis e c. s.n.c.",
        "href": "/Azienda_AVEA-DI-BESSOLO-ELVIS-E-C-SNC",
        "href_details": "https://www.informazione-aziende.it/Azienda_AVEA-DI-BESSOLO-ELVIS-E-C-SNC"
    },
    {
        "nome": "Bar ristorante la trava' di gaudino alessandro e gaudino flavio s.n.c.",
        "href": "/Azienda_BAR-RISTORANTE-LA-TRAVA-DI-GAUDINO-ALESSANDRO-E-GAUDINO-FLAVIO-SNC",
        "href_details": "https://www.informazione-aziende.it/Azienda_BAR-RISTORANTE-LA-TRAVA-DI-GAUDINO-ALESSANDRO-E-GAUDINO-FLAVIO-SNC"
    },
    {
        "nome": "Nisse sas di merlo gian michele & c.",
        "href": "/Azienda_NISSE-SAS-DI-MERLO-GIAN-MICHELE-C",
        "href_details": "https://www.informazione-aziende.it/Azienda_NISSE-SAS-DI-MERLO-GIAN-MICHELE-C"
    },
    {
        "nome": "Camtom sas di priuli luca",
        "href": "/Azienda_CAMTOM-SAS-DI-PRIULI-LUCA",
        "href_details": "https://www.informazione-aziende.it/Azienda_CAMTOM-SAS-DI-PRIULI-LUCA"
    },
    {
        "nome": "Frisco s.a.s. di francesconi sandro e c.",
        "href": "/Azienda_FRISCO-SAS-DI-FRANCESCONI-SANDRO-E-C",
        "href_details": "https://www.informazione-aziende.it/Azienda_FRISCO-SAS-DI-FRANCESCONI-SANDRO-E-C"
    },
    {
        "nome": "Azienda agricola bianco luigi",
        "href": "/Azienda_AZIENDA-AGRICOLA-BIANCO-LUIGI",
        "href_details": "https://www.informazione-aziende.it/Azienda_AZIENDA-AGRICOLA-BIANCO-LUIGI"
    },
    {
        "nome": "Global one s.a.s. di ronchi diego & c.",
        "href": "/Azienda_GLOBAL-ONE-SAS-DI-RONCHI-DIEGO-C",
        "href_details": "https://www.informazione-aziende.it/Azienda_GLOBAL-ONE-SAS-DI-RONCHI-DIEGO-C"
    },
    {
        "nome": "Crazy village s.a.s. di suero clemente siglabile crazy village s.a.s.",
        "href": "/Azienda_CRAZY-VILLAGE-SAS-DI-SUERO-CLEMENTE-SIGLABILE-CRAZY-VILLAGE-SAS",
        "href_details": "https://www.informazione-aziende.it/Azienda_CRAZY-VILLAGE-SAS-DI-SUERO-CLEMENTE-SIGLABILE-CRAZY-VILLAGE-SAS"
    },
    {
        "nome": "Siks - societa' semplice",
        "href": "/Azienda_SIKS-SOCIETA-SEMPLICE",
        "href_details": "https://www.informazione-aziende.it/Azienda_SIKS-SOCIETA-SEMPLICE"
    },
    {
        "nome": "Nestalia s.r.l.",
        "href": "/Azienda_NESTALIA-SRL",
        "href_details": "https://www.informazione-aziende.it/Azienda_NESTALIA-SRL"
    },
    {
        "nome": "Orchidea di mosso ezio e c. s.n.c.",
        "href": "/Azienda_ORCHIDEA-DI-MOSSO-EZIO-E-C-SNC",
        "href_details": "https://www.informazione-aziende.it/Azienda_ORCHIDEA-DI-MOSSO-EZIO-E-C-SNC"
    },
    {
        "nome": "Pro-tab di pronesti sheila",
        "href": "/Azienda_PRO-TAB-DI-PRONESTI-SHEILA",
        "href_details": "https://www.informazione-aziende.it/Azienda_PRO-TAB-DI-PRONESTI-SHEILA"
    },
    {
        "nome": "Fontana carlo guido",
        "href": "/Azienda_FONTANA-CARLO-GUIDO",
        "href_details": "https://www.informazione-aziende.it/Azienda_FONTANA-CARLO-GUIDO"
    },
    {
        "nome": "B.v.l. di bessolo veneria luca",
        "href": "/Azienda_BVL-DI-BESSOLO-VENERIA-LUCA",
        "href_details": "https://www.informazione-aziende.it/Azienda_BVL-DI-BESSOLO-VENERIA-LUCA"
    },
    {
        "nome": "Canaveselab3.0 snc di scagnolari sonia",
        "href": "/Azienda_CANAVESELAB30-SNC-DI-SCAGNOLARI-SONIA",
        "href_details": "https://www.informazione-aziende.it/Azienda_CANAVESELAB30-SNC-DI-SCAGNOLARI-SONIA"
    },
    {
        "nome": "Gaudino fabrizio",
        "href": "/Azienda_GAUDINO-FABRIZIO",
        "href_details": "https://www.informazione-aziende.it/Azienda_GAUDINO-FABRIZIO"
    },
    {
        "nome": "E.ca. evoluzione calore di costa andrea",
        "href": "/Azienda_ECA-EVOLUZIONE-CALORE-DI-COSTA-ANDREA",
        "href_details": "https://www.informazione-aziende.it/Azienda_ECA-EVOLUZIONE-CALORE-DI-COSTA-ANDREA"
    },
    {
        "nome": "Magarini massimo",
        "href": "/Azienda_MAGARINI-MASSIMO",
        "href_details": "https://www.informazione-aziende.it/Azienda_MAGARINI-MASSIMO"
    },
    {
        "nome": "Darkem s.r.l.",
        "href": "/Azienda_DARKEM-SRL",
        "href_details": "https://www.informazione-aziende.it/Azienda_DARKEM-SRL"
    },
    {
        "nome": "Francia francesco",
        "href": "/Azienda_FRANCIA-FRANCESCO",
        "href_details": "https://www.informazione-aziende.it/Azienda_FRANCIA-FRANCESCO"
    },
    {
        "nome": "Bianco mariangela",
        "href": "/Azienda_BIANCO-MARIANGELA",
        "href_details": "https://www.informazione-aziende.it/Azienda_BIANCO-MARIANGELA"
    },
    {
        "nome": "Cooperativa edile canavesana societa' coperativa in liquidazione",
        "href": "/Azienda_COOPERATIVA-EDILE-CANAVESANA-SOCIETA-COPERATIVA",
        "href_details": "https://www.informazione-aziende.it/Azienda_COOPERATIVA-EDILE-CANAVESANA-SOCIETA-COPERATIVA"
    },
    {
        "nome": "Il girasole di lesca diego",
        "href": "/Azienda_IL-GIRASOLE-DI-LESCA-DIEGO",
        "href_details": "https://www.informazione-aziende.it/Azienda_IL-GIRASOLE-DI-LESCA-DIEGO"
    },
    {
        "nome": "Cornea aurel",
        "href": "/Azienda_CORNEA-AUREL",
        "href_details": "https://www.informazione-aziende.it/Azienda_CORNEA-AUREL"
    }
]